asyncpy/__init__.py
asyncpy/demo_middleware.py
asyncpy/exceptions.py
asyncpy/middleware.py
asyncpy/pipelines.py
asyncpy/request.py
asyncpy/response.py
asyncpy/settings.py
asyncpy/spider.py
asyncpy/templates/__init__.py
asyncpy/templates/middlewares.py
asyncpy/templates/pipelines.py
asyncpy/templates/settings.py
asyncpy/templates/spiders/__init__.py
asyncpy/templates/spiders/templates.py
asyncpy/tools/__init__.py
asyncpy/tools/get_attr.py
asyncpy/tools/log.py
asyncpy-1.2.0.dist-info/METADATA
asyncpy-1.2.0.dist-info/WHEEL
asyncpy-1.2.0.dist-info/entry_points.txt
asyncpy-1.2.0.dist-info/top_level.txt
asyncpy-1.2.0.dist-info/RECORD
