Metadata-Version: 1.2
Name: asyncpy
Version: 1.2.0
Summary: Use asyncio and aiohttp's concatenated web crawler framework
Home-page: https://github.com/lixi5338619/asyncpy.git
Author: lx
Author-email: 125066648@qq.com
Maintainer: lx
License: UNKNOWN
Keywords: python web crawl asyncio
Platform: all
Classifier: Programming Language :: Python :: 3
Requires-Python: >=3.6
